mmutils/__init__.py
mmutils/decorator_utils/Mdecorator.py
mmutils/decorator_utils/__init__.py
mmutils/file_utils/Mfile.py
mmutils/file_utils/__init__.py
mmutils/log_utils/Mlog.py
mmutils/log_utils/__init__.py
mmutils/ocr_utils/Mcaptcha.py
mmutils/ocr_utils/__init__.py
mmutils/proxy_utils/Mproxy.py
mmutils/proxy_utils/__init__.py
mmutils/spider_utils/Mrequests.py
mmutils/spider_utils/__init__.py
mmutils/str_utils/Mstr.py
mmutils/str_utils/__init__.py
mmutils/url_utils/Murl.py
mmutils/url_utils/__init__.py
MMutils-0.0.4.dist-info/METADATA
MMutils-0.0.4.dist-info/WHEEL
MMutils-0.0.4.dist-info/top_level.txt
MMutils-0.0.4.dist-info/RECORD
