Metadata-Version: 2.1
Name: MMutils
Version: 0.0.4
Summary: 自用模块
Author: MoMingLog
Author-email: 
License: MIT
Classifier: Development Status :: 1 - Planning
Classifier: Intended Audience :: Developers
Classifier: Programming Language :: Python :: 3
Classifier: Operating System :: Unix
Classifier: Operating System :: MacOS :: MacOS X
Classifier: Operating System :: Microsoft :: Windows
Requires-Dist: Faker (>=18.7.0)
Requires-Dist: ddddocr (>=1.4.7)
Requires-Dist: requests (>=2.30.0)
Requires-Dist: loguru (>=0.7.0)
Requires-Dist: lxml (>=4.9.2)
